[
 {
  "measurement": "timer",
  "epoch": 0.07142857142857142,
  "value": 0.0002720355987548828,
  "event": "load_data"
 },
 {
  "measurement": "timer",
  "epoch": 0.07142857142857142,
  "value": 0.24320578575134277,
  "event": "forward_pass"
 },
 {
  "measurement": "timer",
  "epoch": 0.07142857142857142,
  "value": 0.4754204750061035,
  "event": "backward_pass"
 },
 {
  "measurement": "timer",
  "epoch": 0.14285714285714285,
  "value": 1.33514404296875e-05,
  "event": "compress_model"
 },
 {
  "measurement": "timer",
  "epoch": 0.14285714285714285,
  "value": 0.4455122947692871,
  "event": "backward_pass"
 },
 {
  "measurement": "timer",
  "epoch": 0.21428571428571427,
  "value": 2.0503997802734375e-05,
  "event": "compress_model"
 },
 {
  "measurement": "timer",
  "epoch": 0.2857142857142857,
  "value": 1.2636184692382812e-05,
  "event": "compress_model"
 },
 {
  "measurement": "timer",
  "epoch": 0.2857142857142857,
  "value": 0.002693653106689453,
  "event": "load_data"
 },
 {
  "measurement": "timer",
  "epoch": 0.6428571428571429,
  "value": 0.45928359031677246,
  "event": "backward_pass"
 },
 {
  "measurement": "timer",
  "epoch": 0.7142857142857143,
  "value": 1.2874603271484375e-05,
  "event": "compress_model"
 },
 {
  "measurement": "timer",
  "epoch": 0.7142857142857143,
  "value": 0.004564762115478516,
  "event": "load_data"
 },
 {
  "measurement": "timer",
  "epoch": 0.8571428571428571,
  "value": 0.22097349166870117,
  "event": "forward_pass"
 },
 {
  "measurement": "timer",
  "epoch": 1.0,
  "value": 1.239776611328125e-05,
  "event": "compress_model"
 },
 {
  "measurement": "runtime",
  "time": "2021-07-19 11:26:04",
  "worker_id": 4,
  "client_id": 7,
  "comm_round": 1,
  "epoch": 1.0,
  "local_index": 14,
  "loss": 1.513048923546034,
  "top1": 34.89461352953587,
  "loss2": 0,
  "split": "train"
 },
 {
  "measurement": "timer",
  "epoch": 1.3571428571428572,
  "value": 0.24277830123901367,
  "event": "forward_pass"
 },
 {
  "measurement": "timer",
  "epoch": 1.5,
  "value": 0.4644148349761963,
  "event": "backward_pass"
 },
 {
  "measurement": "timer",
  "epoch": 1.7142857142857142,
  "value": 1.3113021850585938e-05,
  "event": "compress_model"
 },
 {
  "measurement": "runtime",
  "time": "2021-07-19 11:26:13",
  "worker_id": 4,
  "client_id": 7,
  "comm_round": 1,
  "epoch": 2.0,
  "local_index": 28,
  "loss": 1.1849515999228948,
  "top1": 53.27868849778901,
  "loss2": 0,
  "split": "train"
 },
 {
  "measurement": "timer",
  "epoch": 0.35714285714285715,
  "value": 0.002758026123046875,
  "event": "load_data"
 },
 {
  "measurement": "timer",
  "epoch": 0.6428571428571429,
  "value": 0.4649384021759033,
  "event": "backward_pass"
 },
 {
  "measurement": "timer",
  "epoch": 0.7857142857142857,
  "value": 0.44877147674560547,
  "event": "backward_pass"
 },
 {
  "measurement": "runtime",
  "time": "2021-07-19 11:27:26",
  "worker_id": 4,
  "client_id": 5,
  "comm_round": 2,
  "epoch": 1.0,
  "local_index": 14,
  "loss": 1.7177436510907962,
  "top1": 1.6393442801625164,
  "loss2": 0.019905361274924715,
  "split": "train"
 },
 {
  "measurement": "timer",
  "epoch": 1.0,
  "value": 0.0017385482788085938,
  "event": "load_data"
 },
 {
  "measurement": "timer",
  "epoch": 1.2142857142857142,
  "value": 0.45615673065185547,
  "event": "backward_pass"
 },
 {
  "measurement": "timer",
  "epoch": 1.3571428571428572,
  "value": 0.698063850402832,
  "event": "forward_pass"
 },
 {
  "measurement": "timer",
  "epoch": 1.4285714285714286,
  "value": 0.7051246166229248,
  "event": "forward_pass"
 },
 {
  "measurement": "runtime",
  "time": "2021-07-19 11:27:43",
  "worker_id": 4,
  "client_id": 5,
  "comm_round": 2,
  "epoch": 2.0,
  "local_index": 28,
  "loss": 1.0898414741355307,
  "top1": 92.15456674473067,
  "loss2": 0.03288170590612872,
  "split": "train"
 },
 {
  "measurement": "timer",
  "epoch": 2.7142857142857144,
  "value": 0.00041961669921875,
  "event": "load_data"
 },
 {
  "measurement": "timer",
  "epoch": 0.0,
  "value": 0.4734375476837158,
  "event": "backward_pass"
 },
 {
  "measurement": "runtime",
  "time": "2021-07-19 11:28:48",
  "worker_id": 4,
  "client_id": 8,
  "comm_round": 3,
  "epoch": 1.0,
  "local_index": 14,
  "loss": 1.9170123645795871,
  "top1": 2.459016429177492,
  "loss2": 0.021278150266241413,
  "split": "train"
 },
 {
  "measurement": "runtime",
  "time": "2021-07-19 11:29:02",
  "worker_id": 4,
  "client_id": 8,
  "comm_round": 3,
  "epoch": 2.0,
  "local_index": 28,
  "loss": 0.950086770766792,
  "top1": 98.24355971896955,
  "loss2": 0.04671741115579281,
  "split": "train"
 },
 {
  "measurement": "timer",
  "epoch": 2.357142857142857,
  "value": 0.6901655197143555,
  "event": "forward_pass"
 },
 {
  "measurement": "runtime",
  "time": "2021-07-19 11:30:13",
  "worker_id": 4,
  "client_id": 10,
  "comm_round": 4,
  "epoch": 1.0,
  "local_index": 14,
  "loss": 1.3020516137049405,
  "top1": 61.94379391100703,
  "loss2": 0.02356801398395096,
  "split": "train"
 },
 {
  "measurement": "runtime",
  "time": "2021-07-19 11:30:28",
  "worker_id": 4,
  "client_id": 10,
  "comm_round": 4,
  "epoch": 2.0,
  "local_index": 28,
  "loss": 0.5417693982498428,
  "top1": 100.0,
  "loss2": 0.03321998992136547,
  "split": "train"
 },
 {
  "measurement": "timer",
  "epoch": 2.0714285714285716,
  "value": 0.6847090721130371,
  "event": "forward_pass"
 },
 {
  "measurement": "runtime",
  "time": "2021-07-19 11:31:39",
  "worker_id": 4,
  "client_id": 10,
  "comm_round": 5,
  "epoch": 1.0,
  "local_index": 14,
  "loss": 0.9217123234299921,
  "top1": 69.3208430913349,
  "loss2": 0.018111765912496233,
  "split": "train"
 },
 {
  "measurement": "timer",
  "epoch": 1.6428571428571428,
  "value": 0.00450587272644043,
  "event": "load_data"
 },
 {
  "measurement": "runtime",
  "time": "2021-07-19 11:31:55",
  "worker_id": 4,
  "client_id": 10,
  "comm_round": 5,
  "epoch": 2.0,
  "local_index": 28,
  "loss": 0.36632341376791516,
  "top1": 100.0,
  "loss2": 0.027598470161544635,
  "split": "train"
 },
 {
  "measurement": "runtime",
  "time": "2021-07-19 11:33:07",
  "worker_id": 4,
  "client_id": 10,
  "comm_round": 6,
  "epoch": 1.0,
  "local_index": 14,
  "loss": 0.48420251371988926,
  "top1": 94.02810304449649,
  "loss2": 0.01929297490564526,
  "split": "train"
 },
 {
  "measurement": "timer",
  "epoch": 1.5714285714285714,
  "value": 0.4744410514831543,
  "event": "backward_pass"
 },
 {
  "measurement": "runtime",
  "time": "2021-07-19 11:33:23",
  "worker_id": 4,
  "client_id": 10,
  "comm_round": 6,
  "epoch": 2.0,
  "local_index": 28,
  "loss": 0.19627680610298273,
  "top1": 100.0,
  "loss2": 0.021397816366243418,
  "split": "train"
 },
 {
  "measurement": "timer",
  "epoch": 3.0,
  "value": 1.3113021850585938e-05,
  "event": "compress_model"
 },
 {
  "measurement": "timer",
  "epoch": 1.0,
  "value": 1.52587890625e-05,
  "event": "compress_model"
 },
 {
  "measurement": "runtime",
  "time": "2021-07-19 11:34:37",
  "worker_id": 4,
  "client_id": 10,
  "comm_round": 7,
  "epoch": 1.0,
  "local_index": 14,
  "loss": 0.1443457432108685,
  "top1": 100.0,
  "loss2": 0.015315783458742242,
  "split": "train"
 },
 {
  "measurement": "runtime",
  "time": "2021-07-19 11:34:44",
  "worker_id": 4,
  "client_id": 10,
  "comm_round": 7,
  "epoch": 2.0,
  "local_index": 28,
  "loss": 0.06486084758013975,
  "top1": 100.0,
  "loss2": 0.01520295327734333,
  "split": "train"
 },
 {
  "measurement": "timer",
  "epoch": 0.5,
  "value": 0.004555702209472656,
  "event": "load_data"
 },
 {
  "measurement": "runtime",
  "time": "2021-07-19 11:35:58",
  "worker_id": 4,
  "client_id": 8,
  "comm_round": 8,
  "epoch": 1.0,
  "local_index": 14,
  "loss": 0.8721837245747971,
  "top1": 75.87822014051523,
  "loss2": 0.02233020963465721,
  "split": "train"
 },
 {
  "measurement": "runtime",
  "time": "2021-07-19 11:36:15",
  "worker_id": 4,
  "client_id": 8,
  "comm_round": 8,
  "epoch": 2.0,
  "local_index": 28,
  "loss": 0.3356468442661701,
  "top1": 100.0,
  "loss2": 0.02786127757499173,
  "split": "train"
 },
 {
  "measurement": "runtime",
  "time": "2021-07-19 11:37:25",
  "worker_id": 4,
  "client_id": 10,
  "comm_round": 9,
  "epoch": 1.0,
  "local_index": 14,
  "loss": 0.7625348963698403,
  "top1": 79.50819672131148,
  "loss2": 0.04240761001962968,
  "split": "train"
 },
 {
  "measurement": "runtime",
  "time": "2021-07-19 11:37:42",
  "worker_id": 4,
  "client_id": 10,
  "comm_round": 9,
  "epoch": 2.0,
  "local_index": 28,
  "loss": 0.11172174692014342,
  "top1": 100.0,
  "loss2": 0.05823552321459426,
  "split": "train"
 },
 {
  "measurement": "runtime",
  "time": "2021-07-19 11:38:59",
  "worker_id": 4,
  "client_id": 10,
  "comm_round": 10,
  "epoch": 1.0,
  "local_index": 14,
  "loss": 0.21597817997323823,
  "top1": 97.65807962529274,
  "loss2": 0.01909585798320642,
  "split": "train"
 },
 {
  "measurement": "runtime",
  "time": "2021-07-19 11:39:16",
  "worker_id": 4,
  "client_id": 10,
  "comm_round": 10,
  "epoch": 2.0,
  "local_index": 28,
  "loss": 0.06282363967224083,
  "top1": 100.0,
  "loss2": 0.022428366013167892,
  "split": "train"
 },
 {
  "measurement": "timer",
  "epoch": 2.0,
  "value": 0.7052056789398193,
  "event": "forward_pass"
 }
]