[
 {
  "measurement": "timer",
  "epoch": 0.022727272727272728,
  "value": 0.00013136863708496094,
  "event": "load_data"
 },
 {
  "measurement": "timer",
  "epoch": 0.022727272727272728,
  "value": 0.09065937995910645,
  "event": "forward_pass"
 },
 {
  "measurement": "timer",
  "epoch": 0.022727272727272728,
  "value": 0.17087912559509277,
  "event": "backward_pass"
 },
 {
  "measurement": "timer",
  "epoch": 0.045454545454545456,
  "value": 1.7642974853515625e-05,
  "event": "compress_model"
 },
 {
  "measurement": "timer",
  "epoch": 0.045454545454545456,
  "value": 0.0002067089080810547,
  "event": "load_data"
 },
 {
  "measurement": "timer",
  "epoch": 0.045454545454545456,
  "value": 0.08866739273071289,
  "event": "forward_pass"
 },
 {
  "measurement": "timer",
  "epoch": 0.06818181818181818,
  "value": 1.7404556274414062e-05,
  "event": "compress_model"
 },
 {
  "measurement": "timer",
  "epoch": 0.06818181818181818,
  "value": 0.0001220703125,
  "event": "load_data"
 },
 {
  "measurement": "timer",
  "epoch": 0.09090909090909091,
  "value": 1.1920928955078125e-05,
  "event": "compress_model"
 },
 {
  "measurement": "timer",
  "epoch": 0.09090909090909091,
  "value": 0.08799958229064941,
  "event": "forward_pass"
 },
 {
  "measurement": "timer",
  "epoch": 0.11363636363636363,
  "value": 0.16514897346496582,
  "event": "backward_pass"
 },
 {
  "measurement": "timer",
  "epoch": 0.13636363636363635,
  "value": 0.0001850128173828125,
  "event": "load_data"
 },
 {
  "measurement": "timer",
  "epoch": 0.1590909090909091,
  "value": 0.08625197410583496,
  "event": "forward_pass"
 },
 {
  "measurement": "timer",
  "epoch": 0.2727272727272727,
  "value": 1.239776611328125e-05,
  "event": "compress_model"
 },
 {
  "measurement": "timer",
  "epoch": 0.8181818181818182,
  "value": 0.00014710426330566406,
  "event": "load_data"
 },
 {
  "measurement": "timer",
  "epoch": 0.8409090909090909,
  "value": 0.08691668510437012,
  "event": "forward_pass"
 },
 {
  "measurement": "timer",
  "epoch": 0.8636363636363636,
  "value": 1.7642974853515625e-05,
  "event": "compress_model"
 },
 {
  "measurement": "timer",
  "epoch": 0.9318181818181818,
  "value": 1.7642974853515625e-05,
  "event": "compress_model"
 },
 {
  "measurement": "timer",
  "epoch": 0.06818181818181818,
  "value": 0.16799163818359375,
  "event": "backward_pass"
 },
 {
  "measurement": "timer",
  "epoch": 0.11363636363636363,
  "value": 0.08624410629272461,
  "event": "forward_pass"
 },
 {
  "measurement": "timer",
  "epoch": 0.18181818181818182,
  "value": 0.1665802001953125,
  "event": "backward_pass"
 },
 {
  "measurement": "timer",
  "epoch": 0.2727272727272727,
  "value": 1.2159347534179688e-05,
  "event": "compress_model"
 },
 {
  "measurement": "timer",
  "epoch": 0.6363636363636364,
  "value": 0.1655867099761963,
  "event": "backward_pass"
 },
 {
  "measurement": "timer",
  "epoch": 0.6590909090909091,
  "value": 0.0862724781036377,
  "event": "forward_pass"
 },
 {
  "measurement": "timer",
  "epoch": 0.11363636363636363,
  "value": 0.16705656051635742,
  "event": "backward_pass"
 },
 {
  "measurement": "timer",
  "epoch": 0.7727272727272727,
  "value": 0.00011277198791503906,
  "event": "load_data"
 },
 {
  "measurement": "timer",
  "epoch": 0.7954545454545454,
  "value": 0.00011181831359863281,
  "event": "load_data"
 },
 {
  "measurement": "timer",
  "epoch": 0.8181818181818182,
  "value": 0.16857671737670898,
  "event": "backward_pass"
 },
 {
  "measurement": "timer",
  "epoch": 0.6590909090909091,
  "value": 1.6450881958007812e-05,
  "event": "compress_model"
 }
]