[
 {
  "measurement": "timer",
  "epoch": 0.07142857142857142,
  "value": 0.0003063678741455078,
  "event": "load_data"
 },
 {
  "measurement": "timer",
  "epoch": 0.07142857142857142,
  "value": 0.07761979103088379,
  "event": "forward_pass"
 },
 {
  "measurement": "timer",
  "epoch": 0.07142857142857142,
  "value": 0.15851521492004395,
  "event": "backward_pass"
 },
 {
  "measurement": "timer",
  "epoch": 0.14285714285714285,
  "value": 1.811981201171875e-05,
  "event": "compress_model"
 },
 {
  "measurement": "timer",
  "epoch": 0.14285714285714285,
  "value": 0.00015282630920410156,
  "event": "load_data"
 },
 {
  "measurement": "timer",
  "epoch": 0.21428571428571427,
  "value": 2.5987625122070312e-05,
  "event": "compress_model"
 },
 {
  "measurement": "timer",
  "epoch": 0.2857142857142857,
  "value": 1.3113021850585938e-05,
  "event": "compress_model"
 },
 {
  "measurement": "timer",
  "epoch": 0.2857142857142857,
  "value": 0.07592606544494629,
  "event": "forward_pass"
 },
 {
  "measurement": "timer",
  "epoch": 0.2857142857142857,
  "value": 0.15451622009277344,
  "event": "backward_pass"
 },
 {
  "measurement": "timer",
  "epoch": 0.35714285714285715,
  "value": 0.00011277198791503906,
  "event": "load_data"
 },
 {
  "measurement": "timer",
  "epoch": 0.35714285714285715,
  "value": 0.0754542350769043,
  "event": "forward_pass"
 },
 {
  "measurement": "runtime",
  "time": "2021-07-16 15:11:03",
  "worker_id": 4,
  "client_id": 7,
  "comm_round": 1,
  "epoch": 1.0,
  "local_index": 14,
  "loss": 1.4946317281879362,
  "top1": 39.9297423976925,
  "loss2": 0,
  "split": "train"
 },
 {
  "measurement": "timer",
  "epoch": 1.2857142857142858,
  "value": 0.00015926361083984375,
  "event": "load_data"
 },
 {
  "measurement": "timer",
  "epoch": 1.5,
  "value": 1.7881393432617188e-05,
  "event": "compress_model"
 },
 {
  "measurement": "timer",
  "epoch": 1.6428571428571428,
  "value": 0.16463637351989746,
  "event": "backward_pass"
 },
 {
  "measurement": "timer",
  "epoch": 1.7857142857142858,
  "value": 1.5020370483398438e-05,
  "event": "compress_model"
 },
 {
  "measurement": "timer",
  "epoch": 1.8571428571428572,
  "value": 0.20551180839538574,
  "event": "backward_pass"
 },
 {
  "measurement": "runtime",
  "time": "2021-07-16 15:11:07",
  "worker_id": 4,
  "client_id": 7,
  "comm_round": 1,
  "epoch": 2.0,
  "local_index": 28,
  "loss": 1.1173874139785767,
  "top1": 51.873536335500674,
  "loss2": 0,
  "split": "train"
 },
 {
  "measurement": "timer",
  "epoch": 2.2857142857142856,
  "value": 0.0001461505889892578,
  "event": "load_data"
 },
 {
  "measurement": "timer",
  "epoch": 2.5,
  "value": 0.08928894996643066,
  "event": "forward_pass"
 },
 {
  "measurement": "timer",
  "epoch": 2.7142857142857144,
  "value": 0.09222865104675293,
  "event": "forward_pass"
 },
 {
  "measurement": "timer",
  "epoch": 0.07142857142857142,
  "value": 0.00046515464782714844,
  "event": "load_data"
 },
 {
  "measurement": "timer",
  "epoch": 0.6428571428571429,
  "value": 0.07596254348754883,
  "event": "forward_pass"
 },
 {
  "measurement": "runtime",
  "time": "2021-07-16 15:11:52",
  "worker_id": 4,
  "client_id": 5,
  "comm_round": 2,
  "epoch": 1.0,
  "local_index": 14,
  "loss": 1.7469359038864423,
  "top1": 7.377049216062738,
  "loss2": 0.0065018447656926,
  "split": "train"
 },
 {
  "measurement": "timer",
  "epoch": 1.2142857142857142,
  "value": 0.07650279998779297,
  "event": "forward_pass"
 },
 {
  "measurement": "timer",
  "epoch": 1.4285714285714286,
  "value": 0.1538093090057373,
  "event": "backward_pass"
 },
 {
  "measurement": "runtime",
  "time": "2021-07-16 15:11:56",
  "worker_id": 4,
  "client_id": 5,
  "comm_round": 2,
  "epoch": 2.0,
  "local_index": 28,
  "loss": 0.8736538969381632,
  "top1": 96.48711943793911,
  "loss2": 0.017081221247166045,
  "split": "train"
 },
 {
  "measurement": "runtime",
  "time": "2021-07-16 15:12:43",
  "worker_id": 4,
  "client_id": 8,
  "comm_round": 3,
  "epoch": 1.0,
  "local_index": 14,
  "loss": 1.8290364234173884,
  "top1": 21.89695550351288,
  "loss2": 0.00842649828363428,
  "split": "train"
 },
 {
  "measurement": "timer",
  "epoch": 1.6428571428571428,
  "value": 0.15661096572875977,
  "event": "backward_pass"
 },
 {
  "measurement": "runtime",
  "time": "2021-07-16 15:12:48",
  "worker_id": 4,
  "client_id": 8,
  "comm_round": 3,
  "epoch": 2.0,
  "local_index": 28,
  "loss": 0.6512747436273293,
  "top1": 100.0,
  "loss2": 0.033238913384058995,
  "split": "train"
 },
 {
  "measurement": "runtime",
  "time": "2021-07-16 15:13:43",
  "worker_id": 4,
  "client_id": 10,
  "comm_round": 4,
  "epoch": 1.0,
  "local_index": 14,
  "loss": 1.1628054829894519,
  "top1": 68.38407494145198,
  "loss2": 0.02305143422052369,
  "split": "train"
 },
 {
  "measurement": "timer",
  "epoch": 1.6428571428571428,
  "value": 0.1671314239501953,
  "event": "backward_pass"
 },
 {
  "measurement": "timer",
  "epoch": 1.9285714285714286,
  "value": 0.07115459442138672,
  "event": "backward_pass"
 },
 {
  "measurement": "runtime",
  "time": "2021-07-16 15:13:49",
  "worker_id": 4,
  "client_id": 10,
  "comm_round": 4,
  "epoch": 2.0,
  "local_index": 28,
  "loss": 0.34018800842119884,
  "top1": 100.0,
  "loss2": 0.05129742196628025,
  "split": "train"
 },
 {
  "measurement": "timer",
  "epoch": 0.5,
  "value": 0.1556100845336914,
  "event": "backward_pass"
 },
 {
  "measurement": "timer",
  "epoch": 0.6428571428571429,
  "value": 0.0001347064971923828,
  "event": "load_data"
 },
 {
  "measurement": "runtime",
  "time": "2021-07-16 15:14:32",
  "worker_id": 4,
  "client_id": 10,
  "comm_round": 5,
  "epoch": 1.0,
  "local_index": 14,
  "loss": 0.7668787559245732,
  "top1": 75.64402810304449,
  "loss2": 0.018219013953585814,
  "split": "train"
 },
 {
  "measurement": "runtime",
  "time": "2021-07-16 15:14:37",
  "worker_id": 4,
  "client_id": 10,
  "comm_round": 5,
  "epoch": 2.0,
  "local_index": 28,
  "loss": 0.20088912738570006,
  "top1": 100.0,
  "loss2": 0.047825561003188057,
  "split": "train"
 },
 {
  "measurement": "runtime",
  "time": "2021-07-16 15:15:23",
  "worker_id": 4,
  "client_id": 10,
  "comm_round": 6,
  "epoch": 1.0,
  "local_index": 14,
  "loss": 0.38518187742183024,
  "top1": 91.80327868852459,
  "loss2": 0.03395300193643961,
  "split": "train"
 },
 {
  "measurement": "runtime",
  "time": "2021-07-16 15:15:28",
  "worker_id": 4,
  "client_id": 10,
  "comm_round": 6,
  "epoch": 2.0,
  "local_index": 28,
  "loss": 0.11427184004135936,
  "top1": 100.0,
  "loss2": 0.0674184822680241,
  "split": "train"
 },
 {
  "measurement": "timer",
  "epoch": 2.642857142857143,
  "value": 1.2159347534179688e-05,
  "event": "compress_model"
 },
 {
  "measurement": "runtime",
  "time": "2021-07-16 15:15:59",
  "worker_id": 4,
  "client_id": 10,
  "comm_round": 7,
  "epoch": 1.0,
  "local_index": 14,
  "loss": 0.092253712889252,
  "top1": 100.0,
  "loss2": 0.05002234038619861,
  "split": "train"
 },
 {
  "measurement": "runtime",
  "time": "2021-07-16 15:16:04",
  "worker_id": 4,
  "client_id": 10,
  "comm_round": 7,
  "epoch": 2.0,
  "local_index": 28,
  "loss": 0.04454798513992888,
  "top1": 100.0,
  "loss2": 0.07625732788994943,
  "split": "train"
 },
 {
  "measurement": "runtime",
  "time": "2021-07-16 15:16:43",
  "worker_id": 4,
  "client_id": 8,
  "comm_round": 8,
  "epoch": 1.0,
  "local_index": 14,
  "loss": 0.6326696217339268,
  "top1": 81.49882903981265,
  "loss2": 0.037270345858165195,
  "split": "train"
 },
 {
  "measurement": "runtime",
  "time": "2021-07-16 15:16:48",
  "worker_id": 4,
  "client_id": 8,
  "comm_round": 8,
  "epoch": 2.0,
  "local_index": 28,
  "loss": 0.18401477613270423,
  "top1": 100.0,
  "loss2": 0.08323682207762496,
  "split": "train"
 },
 {
  "measurement": "runtime",
  "time": "2021-07-16 15:17:37",
  "worker_id": 4,
  "client_id": 10,
  "comm_round": 9,
  "epoch": 1.0,
  "local_index": 14,
  "loss": 0.7232983447698575,
  "top1": 79.7423887587822,
  "loss2": 0.032625947326456635,
  "split": "train"
 },
 {
  "measurement": "runtime",
  "time": "2021-07-16 15:17:44",
  "worker_id": 4,
  "client_id": 10,
  "comm_round": 9,
  "epoch": 2.0,
  "local_index": 28,
  "loss": 0.09085128885591337,
  "top1": 100.0,
  "loss2": 0.03871449396293392,
  "split": "train"
 },
 {
  "measurement": "runtime",
  "time": "2021-07-16 15:18:56",
  "worker_id": 4,
  "client_id": 10,
  "comm_round": 10,
  "epoch": 1.0,
  "local_index": 14,
  "loss": 0.19073007585572416,
  "top1": 97.65807962529274,
  "loss2": 0.030740388139070336,
  "split": "train"
 },
 {
  "measurement": "timer",
  "epoch": 1.0714285714285714,
  "value": 0.0002498626708984375,
  "event": "load_data"
 },
 {
  "measurement": "runtime",
  "time": "2021-07-16 15:19:07",
  "worker_id": 4,
  "client_id": 10,
  "comm_round": 10,
  "epoch": 2.0,
  "local_index": 28,
  "loss": 0.05960226230829326,
  "top1": 100.0,
  "loss2": 0.04614112330753295,
  "split": "train"
 }
]